MANIFEST.in
README.rst
setup.cfg
setup.py
django_htmlmin_ajax.egg-info/PKG-INFO
django_htmlmin_ajax.egg-info/SOURCES.txt
django_htmlmin_ajax.egg-info/dependency_links.txt
django_htmlmin_ajax.egg-info/entry_points.txt
django_htmlmin_ajax.egg-info/requires.txt
django_htmlmin_ajax.egg-info/top_level.txt
htmlmin/__init__.py
htmlmin/commands.py
htmlmin/decorators.py
htmlmin/middleware.py
htmlmin/minify.py
htmlmin/util.py