Metadata-Version: 1.1
Name: django-htmlmin-ajax
Version: 0.11.0
Summary: HTML minifier for Python frameworks (not only Django, despite the name).
Home-page: UNKNOWN
Author: Mario Perdomo
Author-email: mariod3w@gmail.com
License: UNKNOWN
Keywords: django,html,minifier,minify
Platform: UNKNOWN
Classifier: Development Status :: 5 - Production/Stable
Classifier: Framework :: Django :: 1.11
Classifier: Framework :: Django :: 2.0
Classifier: Framework :: Django :: 2.1
Classifier: Framework :: Django
Classifier: Intended Audience :: Developers
Classifier: License :: OSI Approved :: BSD License
Classifier: Natural Language :: English
Classifier: Operating System :: OS Independent
Classifier: Programming Language :: Python :: 2.7
Classifier: Programming Language :: Python :: 3
Classifier: Programming Language :: Python :: 3.4
Classifier: Programming Language :: Python :: 3.5
Classifier: Programming Language :: Python :: 3.6
Classifier: Programming Language :: Python :: 3.7
Classifier: Topic :: Text Processing :: Markup :: HTML
